opticedge_cloud_utils/__init__.py
opticedge_cloud_utils/auth.py
opticedge_cloud_utils/merge.py
opticedge_cloud_utils/mongo.py
opticedge_cloud_utils/mongo_cache.py
opticedge_cloud_utils/pub.py
opticedge_cloud_utils/secrets.py
opticedge_cloud_utils/task.py
opticedge_cloud_utils-1.0.10.dist-info/METADATA
opticedge_cloud_utils-1.0.10.dist-info/WHEEL
opticedge_cloud_utils-1.0.10.dist-info/top_level.txt
opticedge_cloud_utils-1.0.10.dist-info/RECORD
