Metadata-Version: 2.4
Name: opticedge_cloud_utils
Version: 1.0.10
Summary: Common utilities for cloud functions
Author-email: velopace <velopace7@gmail.com>
License: MIT
Requires-Dist: google-api-core>=2.25.1
Requires-Dist: google-auth>=2.38.0
Requires-Dist: google-auth-oauthlib>=1.2.1
Requires-Dist: google-cloud-secret-manager>=2.23.3
Requires-Dist: google-cloud-pubsub>=2.31.1
Requires-Dist: google-cloud-tasks>=2.19.1
Requires-Dist: protobuf>=5.29.4
Requires-Dist: pymongo>=4.16.0
Provides-Extra: dev
Requires-Dist: build>=1.3.0; extra == "dev"
Requires-Dist: coverage>=7.10.2; extra == "dev"
Requires-Dist: pytest>=8.4.1; extra == "dev"
Requires-Dist: pytest-cov>=6.2.1; extra == "dev"
Requires-Dist: twine>=6.1.0; extra == "dev"
Requires-Dist: toml>=0.10.2; extra == "dev"
